Metadata-Version: 2.1
Name: aviary-genome
Version: 0.5.2
Summary: aviary - metagenomics pipeline using long and short reads
Home-page: https://github.com/rhysnewell/aviary
Author: Rhys Newell
Author-email: rhys.newell94@gmail.com
License: GPL-3.0
Classifier: Topic :: Scientific/Engineering :: Bio-Informatics
License-File: LICENSE
Requires-Dist: snakemake
Requires-Dist: numpy
Requires-Dist: ruamel.yaml (>=0.15.99)
Requires-Dist: pandas
Requires-Dist: biopython
